{
  "name": "Lumisovellus Dev",
  "dockerComposeFile": "../infra/docker/docker-compose.dev.yml",
  "service": "dev",
  "workspaceFolder": "/workspace",
  "customizations": {
    "vscode": {
      "extensions": [
        "dbaeumer.vscode-eslint",
        "esbenp.prettier-vscode",
        "dart-code.flutter",
        "prisma.prisma"
      ]
    }
  },
  "postCreateCommand": "(adb connect host.docker.internal:5555 || true) && (adb reverse tcp:3001 tcp:3001 || true) && cd apps/mobile && flutter pub get",
  "forwardPorts": [3000, 8080]
}
